{"skeleton":{"hash":"jtm+5g8cDkzn4wz6h9V7Y1tMDh4","spine":"3.8.99","x":93.43,"y":-23.09,"width":1896.99,"height":1176.99,"images":"./images/","audio":""},"bones":[{"name":"root"},{"name":"bone","parent":"root","x":1002.1,"y":448.91},{"name":"dk_body","parent":"bone","length":87.85,"rotation":78.87,"x":-8.22,"y":20.56},{"name":"dk_body2","parent":"dk_body","length":70.78,"rotation":-1.18,"x":87.85},{"name":"dk_tou","parent":"dk_body2","length":97.16,"rotation":-0.53,"x":70.76,"y":0.48},{"name":"dk_ysb","parent":"dk_body2","length":57.71,"rotation":-87.33,"x":49.7,"y":-76.46},{"name":"dk_yxb","parent":"dk_ysb","length":73.38,"rotation":-8.99,"x":57.23,"y":0.27},{"name":"dk_yst","parent":"dk_body","length":34.81,"rotation":-145.94,"x":40.3,"y":-78.65},{"name":"dk_yxt","parent":"dk_yst","length":85.92,"rotation":-11.62,"x":35.35,"y":0.22},{"name":"dk_zst","parent":"dk_body","length":51.89,"rotation":131.33,"x":40.31,"y":45.87},{"name":"dk_zxt","parent":"dk_zst","length":77.97,"rotation":8.13,"x":52.61,"y":0.09},{"name":"dk_zsb","parent":"dk_body2","length":53.31,"rotation":85.11,"x":44.69,"y":68.72},{"name":"dk_zxb","parent":"dk_zsb","length":76.22,"rotation":4.02,"x":52.55,"y":0.11},{"name":"dk_bz","parent":"dk_tou","x":114.05,"y":39.94},{"name":"dk_x","parent":"dk_tou","length":19.69,"rotation":-30.98,"x":215.23,"y":-27.46},{"name":"dk_x2","parent":"dk_x","length":17.84,"rotation":-17.55,"x":19.69},{"name":"dk_q","parent":"dk_x2","length":22.54,"rotation":-5.55,"x":18.3,"y":-0.08},{"name":"dk_zui","parent":"dk_bz","length":35.48,"rotation":-177.68,"x":-39.93,"y":-9.23},{"name":"dk_ymm","parent":"dk_bz","length":20.13,"rotation":-54.37,"x":97.11,"y":-46.18},{"name":"dk_zmm","parent":"dk_bz","length":16.29,"rotation":42.79,"x":93.92,"y":-0.63},{"name":"yuan2","parent":"root","x":1034.5,"y":610.5},{"name":"yuan1","parent":"root","rotation":90,"x":1034.5,"y":610.5},{"name":"d1","parent":"root","length":68.5,"rotation":-125.92,"x":158.53,"y":130.82},{"name":"x6","parent":"root","rotation":32.7,"x":407.03,"y":186.02,"color":"ff0000ff"},{"name":"l2","parent":"root","rotation":9.59,"x":229.42,"y":546.02,"color":"ff0000ff"},{"name":"x1","parent":"root","rotation":4.76,"x":1395.82,"y":169.83,"scaleX":0.7327,"scaleY":0.7327,"color":"ff0000ff"},{"name":"x4","parent":"root","rotation":-16,"x":509.06,"y":382.7,"scaleX":1.1343,"scaleY":1.1343,"color":"ff0000ff"},{"name":"l3","parent":"root","rotation":-1.85,"x":679.57,"y":302.39,"scaleX":0.8217,"scaleY":0.8217,"color":"ff0000ff"},{"name":"x2","parent":"root","rotation":35.42,"x":555.7,"y":1100.67,"scaleX":0.8521,"scaleY":0.8521,"color":"ff0000ff"},{"name":"l1","parent":"root","rotation":24.54,"x":623.84,"y":971.07,"scaleX":0.7902,"scaleY":0.7902,"color":"ff0000ff"},{"name":"f1","parent":"root","rotation":-46.55,"x":1941.58,"y":293.87,"color":"ff0000ff"},{"name":"f2","parent":"root","x":954.91,"y":915.13,"scaleX":0.7721,"scaleY":0.7721,"color":"ff0000ff"},{"name":"f3","parent":"root","x":1169.71,"y":1009.61,"scaleX":0.5757,"scaleY":0.5757,"color":"ff0000ff"},{"name":"x3","parent":"root","rotation":3.12,"x":1364.46,"y":899.22,"color":"ff0000ff"},{"name":"l4","parent":"root","rotation":25.9,"x":861.23,"y":95.54,"color":"ff0000ff"},{"name":"d2","parent":"root","x":1297.89,"y":59.56,"color":"ff0000ff"},{"name":"f5","parent":"root","x":1729.89,"y":46.31,"color":"ff0000ff"},{"name":"x5","parent":"root","rotation":6.54,"x":1501.01,"y":443.81,"color":"ff0000ff"},{"name":"l6","parent":"root","rotation":-0.43,"x":1639.88,"y":528.12,"scaleX":0.7477,"scaleY":0.7477,"color":"ff0000ff"},{"name":"f4","parent":"root","rotation":48.43,"x":1117.39,"y":214.62,"scaleX":0.7012,"scaleY":0.7012,"color":"ff0000ff"},{"name":"d5","parent":"root","x":1757.3,"y":331.46,"color":"ff0000ff"},{"name":"d3","parent":"root","x":1646.56,"y":791.75,"color":"ff0000ff"},{"name":"d4","parent":"root","length":65.09,"rotation":-24.2,"x":1884.02,"y":640.98},{"name":"l5","parent":"root","rotation":24.35,"x":1833.23,"y":968.62,"color":"ff0000ff"},{"name":"lz6","parent":"root","x":512.23,"y":466},{"name":"lz4","parent":"root","x":572.77,"y":546.72},{"name":"lz7","parent":"root","x":818.59,"y":984.78},{"name":"lz2","parent":"root","x":881.48,"y":592.36},{"name":"lz1","parent":"root","x":1104.78,"y":333.14},{"name":"lz3","parent":"root","x":1205.56,"y":107.37},{"name":"lz8","parent":"root","x":1328.12,"y":287.1},{"name":"lz9","parent":"root","x":1451.36,"y":544.02},{"name":"lz5","parent":"root","x":1233.73,"y":525.31},{"name":"lz10","parent":"root","x":1478.85,"y":963.13},{"name":"x7","parent":"root","rotation":6.34,"x":141.31,"y":931.89,"color":"ff0000ff"},{"name":"l7","parent":"root","rotation":64.18,"x":373.96,"y":646.58,"scaleX":0.564,"scaleY":0.564,"color":"ff0000ff"},{"name":"f6","parent":"root","rotation":82.96,"x":627.67,"y":717.68,"color":"ff0000ff"},{"name":"l8","parent":"root","rotation":72.41,"x":1527.23,"y":226.13,"scaleX":0.6358,"scaleY":0.6358,"color":"ff0000ff"},{"name":"x8","parent":"root","rotation":17.71,"x":1562.6,"y":38.38,"scaleX":1.1343,"scaleY":1.1343,"color":"ff0000ff"},{"name":"l9","parent":"root","rotation":0.02,"x":1434.77,"y":1098.36,"scaleX":0.629,"scaleY":0.629,"color":"ff0000ff"},{"name":"d6","parent":"root","rotation":-79.9,"x":299.84,"y":362.05,"color":"ff0000ff"},{"name":"l10","parent":"root","rotation":72.94,"x":1497.94,"y":717.02,"scaleX":0.9904,"scaleY":0.9904,"color":"ff0000ff"},{"name":"d7","parent":"root","rotation":-68.09,"x":424.5,"y":869.46,"color":"ff0000ff"},{"name":"d8","parent":"root","length":65.09,"rotation":-128.6,"x":1035.27,"y":640.98},{"name":"lz11","parent":"root","x":1478.85,"y":963.13},{"name":"lz12","parent":"root","x":1451.36,"y":544.02},{"name":"lz13","parent":"root","x":1328.12,"y":287.1},{"name":"lz14","parent":"root","x":818.59,"y":984.78},{"name":"lz15","parent":"root","x":512.23,"y":466},{"name":"lz16","parent":"root","x":1233.73,"y":525.31},{"name":"lz17","parent":"root","x":572.77,"y":546.72},{"name":"lz18","parent":"root","x":1205.56,"y":107.37},{"name":"lz19","parent":"root","x":881.48,"y":592.36},{"name":"lz20","parent":"root","x":1104.78,"y":333.14}],"slots":[{"name":"d8","bone":"d8","attachment":"d4"},{"name":"d5","bone":"d5","attachment":"d5"},{"name":"d7","bone":"d7","attachment":"d5"},{"name":"d4","bone":"d4","attachment":"d4"},{"name":"d3","bone":"d3","attachment":"d3"},{"name":"d2","bone":"d2","attachment":"d2"},{"name":"d6","bone":"d6","attachment":"d2"},{"name":"d1","bone":"d1","attachment":"d1"},{"name":"f5","bone":"f5","attachment":"f5"},{"name":"f4","bone":"f4","attachment":"f4"},{"name":"f6","bone":"f6","attachment":"f4"},{"name":"f3","bone":"f3","attachment":"f3"},{"name":"f2","bone":"f2","attachment":"f2"},{"name":"f1","bone":"f1","attachment":"f1"},{"name":"l6","bone":"l6","attachment":"l6"},{"name":"l7","bone":"l7","attachment":"l6"},{"name":"l5","bone":"l5","attachment":"l5"},{"name":"l8","bone":"l8","attachment":"l5"},{"name":"l4","bone":"l4","attachment":"l4"},{"name":"l9","bone":"l9","attachment":"l4"},{"name":"l3","bone":"l3","attachment":"l3"},{"name":"l2","bone":"l2","attachment":"l2"},{"name":"l10","bone":"l10","attachment":"l2"},{"name":"l1","bone":"l1","attachment":"l1"},{"name":"x6","bone":"x6","attachment":"x6"},{"name":"x5","bone":"x5","attachment":"x5"},{"name":"x4","bone":"x4","attachment":"x4"},{"name":"x8","bone":"x8","attachment":"x4"},{"name":"x3","bone":"x3","attachment":"x3"},{"name":"x2","bone":"x2","attachment":"x2"},{"name":"x1","bone":"x1","attachment":"x1"},{"name":"x7","bone":"x7","attachment":"x1"},{"name":"yuan1","bone":"yuan1"},{"name":"yuan2","bone":"yuan2"},{"name":"lz10","bone":"lz10","attachment":"lz10"},{"name":"lz11","bone":"lz11","attachment":"lz10"},{"name":"lz9","bone":"lz9","attachment":"lz9"},{"name":"lz12","bone":"lz12","attachment":"lz9"},{"name":"lz8","bone":"lz8","attachment":"lz8"},{"name":"lz13","bone":"lz13","attachment":"lz8"},{"name":"lz7","bone":"lz7","attachment":"lz7"},{"name":"lz14","bone":"lz14","attachment":"lz7"},{"name":"lz6","bone":"lz6","attachment":"lz6"},{"name":"lz15","bone":"lz15","attachment":"lz6"},{"name":"lz5","bone":"lz5","attachment":"lz5"},{"name":"lz16","bone":"lz16","attachment":"lz5"},{"name":"lz4","bone":"lz4","attachment":"lz4"},{"name":"lz17","bone":"lz17","attachment":"lz4"},{"name":"lz3","bone":"lz3","attachment":"lz3"},{"name":"lz18","bone":"lz18","attachment":"lz3"},{"name":"lz2","bone":"lz2","attachment":"lz2"},{"name":"lz19","bone":"lz19","attachment":"lz2"},{"name":"lz1","bone":"lz1","attachment":"lz1"},{"name":"lz20","bone":"lz20","attachment":"lz1"},{"name":"dk_zxb","bone":"dk_zxb","attachment":"dk_zxb"},{"name":"dk_zst","bone":"dk_zst","attachment":"dk_zst"},{"name":"dk_zxt","bone":"dk_zxt","attachment":"dk_zxt"},{"name":"dk_q","bone":"dk_q","attachment":"dk_q"},{"name":"dk_x","bone":"dk_x","attachment":"dk_x"},{"name":"dk_zsb","bone":"dk_zsb","attachment":"dk_zsb"},{"name":"dk_tou","bone":"dk_tou","attachment":"dk_tou"},{"name":"dk_eye","bone":"dk_bz","attachment":"dk_eye"},{"name":"dk_zmm","bone":"dk_zmm","attachment":"dk_zmm"},{"name":"dk_ymm","bone":"dk_ymm","attachment":"dk_ymm"},{"name":"dk_bz","bone":"dk_bz","attachment":"dk_bz"},{"name":"dk_zui","bone":"dk_zui","attachment":"dk_zui"},{"name":"dk_body","bone":"dk_body","attachment":"dk_body"},{"name":"dk_ysb","bone":"dk_ysb","attachment":"dk_ysb"},{"name":"dk_yxb","bone":"dk_yxb","attachment":"dk_yxb"},{"name":"dk_yst","bone":"dk_yst","attachment":"dk_yst"},{"name":"dk_yxt","bone":"dk_yxt","attachment":"dk_yxt"},{"name":"dk_zcq","bone":"dk_zxb","attachment":"dk_zcq"},{"name":"dk_ycq","bone":"dk_yxb","attachment":"dk_ycq"}],"skins":[{"name":"default","attachments":{"d1":{"d1":{"type":"mesh","uvs":[1,1,0,1,0,0,1,0],"triangles":[1,2,3,1,3,0],"vertices":[68.88,66.54,112.3,6.61,-0.27,-74.94,-43.68,-15.01],"hull":4,"edges":[0,2,2,4,4,6,0,6],"width":74,"height":139}},"d2":{"d2":{"type":"mesh","uvs":[1,1,0,1,0,0,1,0],"triangles":[1,2,3,1,3,0],"vertices":[22.88,-39.26,-11.12,-39.26,-11.12,35.74,22.88,35.74],"hull":4,"edges":[0,2,2,4,4,6,0,6],"width":34,"height":75}},"d3":{"d3":{"type":"mesh","uvs":[1,1,0,1,0,0,1,0],"triangles":[1,2,3,1,3,0],"vertices":[26.29,-30.66,-38.71,-30.66,-38.71,17.34,26.29,17.34],"hull":4,"edges":[0,2,2,4,4,6,0,6],"width":65,"height":48}},"d4":{"d4":{"type":"mesh","uvs":[1,1,0,1,0,0,1,0],"triangles":[1,2,3,1,3,0],"vertices":[95.64,28.89,72.14,-49.67,-36.12,-17.29,-12.61,61.27],"hull":4,"edges":[0,2,2,4,4,6,0,6],"width":82,"height":113}},"d5":{"d5":{"type":"mesh","uvs":[1,1,0,1,0,0,1,0],"triangles":[1,2,3,1,3,0],"vertices":[61.11,-27.88,-48.89,-27.88,-48.89,14.12,61.11,14.12],"hull":4,"edges":[0,2,2,4,4,6,0,6],"width":110,"height":42}},"d6":{"d2":{"type":"mesh","uvs":[1,1,0,1,0,0,1,0],"triangles":[1,2,3,1,3,0],"vertices":[22.88,-39.26,-11.12,-39.26,-11.12,35.74,22.88,35.74],"hull":4,"edges":[0,2,2,4,4,6,0,6],"width":34,"height":75}},"d7":{"d5":{"type":"mesh","uvs":[1,1,0,1,0,0,1,0],"triangles":[1,2,3,1,3,0],"vertices":[61.11,-27.88,-48.89,-27.88,-48.89,14.12,61.11,14.12],"hull":4,"edges":[0,2,2,4,4,6,0,6],"width":110,"height":42}},"d8":{"d4":{"type":"mesh","uvs":[1,1,0,1,0,0,1,0],"triangles":[1,2,3,1,3,0],"vertices":[95.64,28.89,72.14,-49.67,-36.12,-17.29,-12.61,61.27],"hull":4,"edges":[0,2,2,4,4,6,0,6],"width":82,"height":113}},"dk_body":{"dk_body":{"type":"mesh","uvs":[0.85893,0.08168,0.92447,0.18321,0.99999,0.23692,0.99999,0.29658,0.9625,0.32974,1,0.51634,1,0.69477,0.93269,0.89388,0.72806,1,0.38758,1,0.13312,0.90271,0,0.68642,0,0.46602,0.06395,0.31588,0.16957,0.13344,0.1492,0.06447,0.19243,0,0.5438,0,0.49729,0.55883,0.52898,0.41345,0.57489,0.20929,0.46096,0.72544],"triangles":[14,15,16,20,17,0,4,1,2,4,2,3,14,17,20,17,14,16,19,14,20,13,14,19,18,13,19,4,5,20,20,0,1,4,20,1,20,5,19,6,19,5,12,13,18,11,12,18,21,11,18,6,18,19,7,18,6,21,18,7,10,11,21,9,10,21,8,9,21,7,8,21],"vertices":[1,3,87.32,-56.31,1,1,3,70.85,-74.19,1,1,3,63.99,-92.15,1,2,2,138.46,-95.7,0.03333,3,52.56,-94.64,0.96667,2,2,130.55,-89.12,0.14444,3,44.51,-88.23,0.85556,2,2,96.2,-104.01,0.36667,3,10.48,-103.82,0.63333,2,2,61.89,-110.76,0.63333,3,-23.69,-111.27,0.36667,2,2,20.83,-104.23,0.85556,3,-64.87,-105.58,0.14444,2,2,-7.99,-65.47,0.96667,3,-94.48,-67.42,0.03333,2,2,-21.98,5.69,0.975,3,-109.93,3.43,0.025,2,2,-13.73,62.55,0.96667,3,-102.85,60.45,0.03333,2,2,22.39,98.55,0.85556,3,-67.47,97.19,0.14444,2,2,64.78,106.89,0.63333,3,-25.26,106.39,0.36667,2,2,96.28,99.2,0.36667,3,6.39,99.35,0.63333,2,2,135.71,84.03,0.14444,3,46.12,84.99,0.85556,2,2,148.14,90.89,0.03333,3,58.41,92.11,0.96667,1,3,72.71,85.8,1,1,3,88.66,12.68,1,2,2,67.37,-0.56,0.63333,3,-20.47,-0.98,0.36667,2,2,96.63,-1.68,0.38333,3,8.81,-1.5,0.61667,2,2,137.78,-3.56,0.24167,3,49.99,-2.53,0.75833,2,2,33.83,0.74,0.85556,3,-54.02,-0.37,0.14444],"hull":18,"edges":[24,26,26,28,28,30,30,32,32,34,34,0,0,2,2,4,4,6,6,8,8,10,10,12,12,14,14,16,22,24,22,20,16,18,20,18,18,42,42,36,36,38,38,40],"width":213,"height":196}},"dk_bz":{"dk_bz":{"type":"mesh","uvs":[1,1,0,1,0,0,1,0],"triangles":[1,2,3,1,3,0],"vertices":[-16.38,-27.11,-26.15,15.8,15.78,25.34,25.55,-17.56],"hull":4,"edges":[0,2,2,4,4,6,0,6],"width":44,"height":43}},"dk_eye":{"dk_eye":{"type":"mesh","uvs":[1,1,0,1,0,0,1,0],"triangles":[1,2,3,1,3,0],"vertices":[-15.22,-108.78,-51.19,49.18,45.34,71.16,81.31,-86.79],"hull":4,"edges":[0,2,2,4,4,6,0,6],"width":162,"height":99}},"dk_q":{"dk_q":{"type":"mesh","uvs":[1,1,0,1,0,0,1,0],"triangles":[1,2,3,1,3,0],"vertices":[36.72,-36.95,-18.47,-13.41,4.68,40.86,59.87,17.31],"hull":4,"edges":[0,2,2,4,4,6,0,6],"width":60,"height":59}},"dk_tou":{"dk_tou":{"type":"mesh","uvs":[1,1,0,1,0,0,1,0],"triangles":[1,2,3,1,3,0],"vertices":[22.7,-216.43,-57.01,133.61,195.53,191.12,275.24,-158.92],"hull":4,"edges":[0,2,2,4,4,6,0,6],"width":359,"height":259}},"dk_x":{"dk_x":{"type":"mesh","uvs":[1,0.14397,0.8669,0.2011,0.73744,0.25767,0.64343,0.30675,0.54567,0.35984,0.43737,0.44389,0.35801,0.51777,0.30082,0.59743,0.22954,0.72402,0.20035,1,0,1,0,0.59825,0.03141,0.51309,0.11083,0.40119,0.18668,0.32388,0.36356,0.1803,0.45682,0.12291,0.55053,0.07076,0.66727,0.0308,0.75724,0,1,0],"triangles":[17,18,2,19,20,0,2,18,1,18,19,1,1,19,0,16,17,3,3,17,2,9,10,8,10,11,8,8,11,7,11,12,7,6,7,13,7,12,13,13,14,6,6,14,5,4,5,15,5,14,15,3,4,16,4,15,16],"vertices":[1,15,19.31,-6.09,1,2,14,29.86,-9.66,0.05666,15,12.61,-6.14,0.94334,2,14,23.59,-7.78,0.22443,15,6.07,-6.24,0.77557,2,14,18.71,-6.73,0.50331,15,1.09,-6.72,0.49669,2,14,13.55,-5.72,0.77999,15,-4.13,-7.31,0.22001,2,14,6.79,-5.6,0.94555,15,-10.61,-9.23,0.05445,1,14,1.34,-6,1,1,14,-3.68,-7.32,1,1,14,-11.06,-10.05,1,1,14,-23.3,-20.02,1,1,14,-29.41,-13.65,1,1,14,-12.88,2.2,1,1,14,-8.42,4.56,1,1,14,-1.4,6.45,1,2,14,4.09,7.09,0.94818,15,-17.01,2.06,0.05182,2,14,15.39,7.14,0.78525,15,-6.26,5.51,0.21475,2,14,20.59,6.45,0.5112,15,-1.09,6.42,0.4888,2,14,25.59,5.53,0.22969,15,3.96,7.05,0.77031,2,14,30.79,3.4,0.05929,15,9.56,6.59,0.94071,1,15,13.87,6.23,1,1,15,23.25,1.11,1],"hull":21,"edges":[38,40,0,40,18,20,16,18,20,22,30,32,32,34,4,6,6,8,34,36,36,38,0,2,2,4,26,28,28,30,8,10,10,12,22,24,24,26,12,14,14,16],"width":44,"height":57}},"dk_ycq":{"dk_ycq":{"type":"mesh","uvs":[1,1,0,1,0,0,1,0],"triangles":[1,2,3,1,3,0],"vertices":[229.47,-78.49,63.63,-134.35,0.74,52.34,166.58,108.2],"hull":4,"edges":[0,2,2,4,4,6,0,6],"width":175,"height":197}},"dk_ymm":{"dk_ymm":{"type":"mesh","uvs":[1,1,0,1,0,0,1,0],"triangles":[1,2,3,1,3,0],"vertices":[36.39,-50.46,-15.24,-28.76,2.2,12.72,53.82,-8.98],"hull":4,"edges":[0,2,2,4,4,6,0,6],"width":56,"height":45}},"dk_ysb":{"dk_ysb":{"type":"mesh","uvs":[1,1,0,1,0,0,1,0],"triangles":[1,2,3,1,3,0],"vertices":[86.91,-25.77,-9.71,-42.16,-20.58,21.92,76.04,38.31],"hull":4,"edges":[0,2,2,4,4,6,0,6],"width":98,"height":65}},"dk_yst":{"dk_yst":{"type":"mesh","uvs":[1,1,0,1,0,0,1,0],"triangles":[1,2,3,1,3,0],"vertices":[86.64,17.82,53.91,-59.54,-28.06,-24.86,4.67,52.5],"hull":4,"edges":[0,2,2,4,4,6,0,6],"width":84,"height":89}},"dk_yxb":{"dk_yxb":{"type":"mesh","uvs":[1,1,0,1,0,0,1,0],"triangles":[1,2,3,1,3,0],"vertices":[155.7,-50.58,8.81,-100.06,-29.18,12.72,117.71,62.19],"hull":4,"edges":[0,2,2,4,4,6,0,6],"width":155,"height":119}},"dk_yxt":{"dk_yxt":{"type":"mesh","uvs":[1,1,0,1,0,0,1,0],"triangles":[1,2,3,1,3,0],"vertices":[164.56,91.7,132.98,-66.17,-42.54,-31.06,-10.97,126.81],"hull":4,"edges":[0,2,2,4,4,6,0,6],"width":161,"height":179}},"dk_zcq":{"dk_zcq":{"type":"mesh","uvs":[1,1,0,1,0,0,1,0],"triangles":[1,2,3,1,3,0],"vertices":[-4.59,89.72,175.54,131.87,216.79,-44.36,36.65,-86.52],"hull":4,"edges":[0,2,2,4,4,6,0,6],"width":185,"height":181}},"dk_zmm":{"dk_zmm":{"type":"mesh","uvs":[1,1,0,1,0,0,1,0],"triangles":[1,2,3,1,3,0],"vertices":[-8.54,0.06,18.93,47.71,43.19,33.73,15.72,-13.92],"hull":4,"edges":[0,2,2,4,4,6,0,6],"width":55,"height":28}},"dk_zsb":{"dk_zsb":{"type":"mesh","uvs":[1,1,0,1,0,0,1,0],"triangles":[1,2,3,1,3,0],"vertices":[-30.15,22.05,58.69,49.54,78.49,-14.47,-10.35,-41.95],"hull":4,"edges":[0,2,2,4,4,6,0,6],"width":93,"height":67}},"dk_zst":{"dk_zst":{"type":"mesh","uvs":[1,1,0,1,0,0,1,0],"triangles":[1,2,3,1,3,0],"vertices":[11.08,67.46,103.56,13.63,59.8,-61.56,-32.68,-7.74],"hull":4,"edges":[0,2,2,4,4,6,0,6],"width":107,"height":87}},"dk_zui":{"dk_zui":{"type":"mesh","uvs":[1,1,0,1,0,0,1,0],"triangles":[1,2,3,1,3,0],"vertices":[36.04,52.5,51.72,-32.06,-8.26,-43.18,-23.94,41.38],"hull":4,"edges":[0,2,2,4,4,6,0,6],"width":86,"height":61}},"dk_zxb":{"dk_zxb":{"type":"mesh","uvs":[1,1,0,1,0,0,1,0],"triangles":[1,2,3,1,3,0],"vertices":[-31.37,35.18,111.76,68.68,137.74,-42.32,-5.39,-75.82],"hull":4,"edges":[0,2,2,4,4,6,0,6],"width":147,"height":114}},"dk_zxt":{"dk_zxt":{"type":"mesh","uvs":[1,1,0,1,0,0,1,0],"triangles":[1,2,3,1,3,0],"vertices":[50.74,123.47,206.06,0.66,104.34,-127.98,-50.98,-5.17],"hull":4,"edges":[0,2,2,4,4,6,0,6],"width":198,"height":164}},"f1":{"f1":{"type":"mesh","uvs":[1,1,0,1,0,0,1,0],"triangles":[1,2,3,1,3,0],"vertices":[32.95,-38.95,-33.05,-38.95,-33.05,36.05,32.95,36.05],"hull":4,"edges":[0,2,2,4,4,6,0,6],"width":66,"height":75}},"f2":{"f2":{"type":"mesh","uvs":[1,1,0,1,0,0,1,0],"triangles":[1,2,3,1,3,0],"vertices":[32.09,-37.13,-30.91,-37.13,-30.91,35.87,32.09,35.87],"hull":4,"edges":[0,2,2,4,4,6,0,6],"width":63,"height":73}},"f3":{"f3":{"type":"mesh","uvs":[1,1,0,1,0,0,1,0],"triangles":[1,2,3,1,3,0],"vertices":[34.29,-38.61,-34.72,-38.61,-34.72,38.39,34.29,38.39],"hull":4,"edges":[0,2,2,4,4,6,0,6],"width":69,"height":77}},"f4":{"f4":{"type":"mesh","uvs":[1,1,0,1,0,0,1,0],"triangles":[1,2,3,1,3,0],"vertices":[32.24,-37.46,-28.76,-37.46,-28.76,34.54,32.24,34.54],"hull":4,"edges":[0,2,2,4,4,6,0,6],"width":61,"height":72}},"f5":{"f5":{"type":"mesh","uvs":[1,1,0,1,0,0,1,0],"triangles":[1,2,3,1,3,0],"vertices":[37.11,-38.31,-33.89,-38.31,-33.89,34.69,37.11,34.69],"hull":4,"edges":[0,2,2,4,4,6,0,6],"width":71,"height":73}},"f6":{"f4":{"type":"mesh","uvs":[1,1,0,1,0,0,1,0],"triangles":[1,2,3,1,3,0],"vertices":[32.24,-37.46,-28.76,-37.46,-28.76,34.54,32.24,34.54],"hull":4,"edges":[0,2,2,4,4,6,0,6],"width":61,"height":72}},"l1":{"l1":{"type":"mesh","uvs":[1,1,0,1,0,0,1,0],"triangles":[1,2,3,1,3,0],"vertices":[50.82,-50.15,-52.18,-50.15,-52.18,51.85,50.82,51.85],"hull":4,"edges":[0,2,2,4,4,6,0,6],"width":103,"height":102}},"l2":{"l2":{"type":"mesh","uvs":[1,1,0,1,0,0,1,0],"triangles":[1,2,3,1,3,0],"vertices":[52.68,-55.06,-51.32,-55.06,-51.32,48.94,52.68,48.94],"hull":4,"edges":[0,2,2,4,4,6,0,6],"width":104,"height":104}},"l3":{"l3":{"type":"mesh","uvs":[1,1,0,1,0,0,1,0],"triangles":[1,2,3,1,3,0],"vertices":[48.6,-50.45,-52.4,-50.45,-52.4,49.55,48.6,49.55],"hull":4,"edges":[0,2,2,4,4,6,0,6],"width":101,"height":100}},"l4":{"l4":{"type":"mesh","uvs":[1,1,0,1,0,0,1,0],"triangles":[1,2,3,1,3,0],"vertices":[51.31,-52.83,-51.69,-52.83,-51.69,49.17,51.31,49.17],"hull":4,"edges":[0,2,2,4,4,6,0,6],"width":103,"height":102}},"l5":{"l5":{"type":"mesh","uvs":[1,1,0,1,0,0,1,0],"triangles":[1,2,3,1,3,0],"vertices":[51.19,-51.06,-50.81,-51.06,-50.81,48.94,51.19,48.94],"hull":4,"edges":[0,2,2,4,4,6,0,6],"width":102,"height":100}},"l6":{"l6":{"type":"mesh","uvs":[1,1,0,1,0,0,1,0],"triangles":[1,2,3,1,3,0],"vertices":[47.65,-50.69,-50.35,-50.69,-50.35,46.31,47.65,46.31],"hull":4,"edges":[0,2,2,4,4,6,0,6],"width":98,"height":97}},"l7":{"l6":{"type":"mesh","uvs":[1,1,0,1,0,0,1,0],"triangles":[1,2,3,1,3,0],"vertices":[47.65,-50.69,-50.35,-50.69,-50.35,46.31,47.65,46.31],"hull":4,"edges":[0,2,2,4,4,6,0,6],"width":98,"height":97}},"l8":{"l5":{"type":"mesh","uvs":[1,1,0,1,0,0,1,0],"triangles":[1,2,3,1,3,0],"vertices":[51.19,-51.06,-50.81,-51.06,-50.81,48.94,51.19,48.94],"hull":4,"edges":[0,2,2,4,4,6,0,6],"width":102,"height":100}},"l9":{"l4":{"type":"mesh","uvs":[1,1,0,1,0,0,1,0],"triangles":[1,2,3,1,3,0],"vertices":[51.31,-52.83,-51.69,-52.83,-51.69,49.17,51.31,49.17],"hull":4,"edges":[0,2,2,4,4,6,0,6],"width":103,"height":102}},"l10":{"l2":{"type":"mesh","uvs":[1,1,0,1,0,0,1,0],"triangles":[1,2,3,1,3,0],"vertices":[52.68,-55.06,-51.32,-55.06,-51.32,48.94,52.68,48.94],"hull":4,"edges":[0,2,2,4,4,6,0,6],"width":104,"height":104}},"lz1":{"lz1":{"type":"mesh","uvs":[1,1,0,1,0,0,1,0],"triangles":[1,2,3,1,3,0],"vertices":[20.22,-20.14,-20.78,-20.14,-20.78,20.86,20.22,20.86],"hull":4,"edges":[0,2,2,4,4,6,0,6],"width":41,"height":41}},"lz2":{"lz2":{"type":"mesh","uvs":[1,1,0,1,0,0,1,0],"triangles":[1,2,3,1,3,0],"vertices":[20.52,-20.36,-20.48,-20.36,-20.48,20.64,20.52,20.64],"hull":4,"edges":[0,2,2,4,4,6,0,6],"width":41,"height":41}},"lz3":{"lz3":{"type":"mesh","uvs":[1,1,0,1,0,0,1,0],"triangles":[1,2,3,1,3,0],"vertices":[26.44,-26.37,-27.56,-26.37,-27.56,27.63,26.44,27.63],"hull":4,"edges":[0,2,2,4,4,6,0,6],"width":54,"height":54}},"lz4":{"lz4":{"type":"mesh","uvs":[1,1,0,1,0,0,1,0],"triangles":[1,2,3,1,3,0],"vertices":[31.23,-30.72,-31.77,-30.72,-31.77,32.28,31.23,32.28],"hull":4,"edges":[0,2,2,4,4,6,0,6],"width":63,"height":63}},"lz5":{"lz5":{"type":"mesh","uvs":[1,1,0,1,0,0,1,0],"triangles":[1,2,3,1,3,0],"vertices":[29.27,-29.31,-29.73,-29.31,-29.73,29.69,29.27,29.69],"hull":4,"edges":[0,2,2,4,4,6,0,6],"width":59,"height":59}},"lz6":{"lz6":{"type":"mesh","uvs":[1,1,0,1,0,0,1,0],"triangles":[1,2,3,1,3,0],"vertices":[28.77,-28,-28.23,-28,-28.23,29,28.77,29],"hull":4,"edges":[0,2,2,4,4,6,0,6],"width":57,"height":57}},"lz7":{"lz7":{"type":"mesh","uvs":[1,1,0,1,0,0,1,0],"triangles":[1,2,3,1,3,0],"vertices":[31.41,-31.78,-31.59,-31.78,-31.59,31.22,31.41,31.22],"hull":4,"edges":[0,2,2,4,4,6,0,6],"width":63,"height":63}},"lz8":{"lz8":{"type":"mesh","uvs":[1,1,0,1,0,0,1,0],"triangles":[1,2,3,1,3,0],"vertices":[32.88,-33.1,-33.12,-33.1,-33.12,32.9,32.88,32.9],"hull":4,"edges":[0,2,2,4,4,6,0,6],"width":66,"height":66}},"lz9":{"lz9":{"type":"mesh","uvs":[1,1,0,1,0,0,1,0],"triangles":[1,2,3,1,3,0],"vertices":[26.64,-26.02,-27.36,-26.02,-27.36,27.98,26.64,27.98],"hull":4,"edges":[0,2,2,4,4,6,0,6],"width":54,"height":54}},"lz10":{"lz10":{"type":"mesh","uvs":[1,1,0,1,0,0,1,0],"triangles":[1,2,3,1,3,0],"vertices":[30.15,-30.13,-28.85,-30.13,-28.85,28.87,30.15,28.87],"hull":4,"edges":[0,2,2,4,4,6,0,6],"width":59,"height":59}},"lz11":{"lz10":{"type":"mesh","uvs":[1,1,0,1,0,0,1,0],"triangles":[1,2,3,1,3,0],"vertices":[30.15,-30.13,-28.85,-30.13,-28.85,28.87,30.15,28.87],"hull":4,"edges":[0,2,2,4,4,6,0,6],"width":59,"height":59}},"lz12":{"lz9":{"type":"mesh","uvs":[1,1,0,1,0,0,1,0],"triangles":[1,2,3,1,3,0],"vertices":[26.64,-26.02,-27.36,-26.02,-27.36,27.98,26.64,27.98],"hull":4,"edges":[0,2,2,4,4,6,0,6],"width":54,"height":54}},"lz13":{"lz8":{"type":"mesh","uvs":[1,1,0,1,0,0,1,0],"triangles":[1,2,3,1,3,0],"vertices":[32.88,-33.1,-33.12,-33.1,-33.12,32.9,32.88,32.9],"hull":4,"edges":[0,2,2,4,4,6,0,6],"width":66,"height":66}},"lz14":{"lz7":{"type":"mesh","uvs":[1,1,0,1,0,0,1,0],"triangles":[1,2,3,1,3,0],"vertices":[31.41,-31.78,-31.59,-31.78,-31.59,31.22,31.41,31.22],"hull":4,"edges":[0,2,2,4,4,6,0,6],"width":63,"height":63}},"lz15":{"lz6":{"type":"mesh","uvs":[1,1,0,1,0,0,1,0],"triangles":[1,2,3,1,3,0],"vertices":[28.77,-28,-28.23,-28,-28.23,29,28.77,29],"hull":4,"edges":[0,2,2,4,4,6,0,6],"width":57,"height":57}},"lz16":{"lz5":{"type":"mesh","uvs":[1,1,0,1,0,0,1,0],"triangles":[1,2,3,1,3,0],"vertices":[29.27,-29.31,-29.73,-29.31,-29.73,29.69,29.27,29.69],"hull":4,"edges":[0,2,2,4,4,6,0,6],"width":59,"height":59}},"lz17":{"lz4":{"type":"mesh","uvs":[1,1,0,1,0,0,1,0],"triangles":[1,2,3,1,3,0],"vertices":[31.23,-30.72,-31.77,-30.72,-31.77,32.28,31.23,32.28],"hull":4,"edges":[0,2,2,4,4,6,0,6],"width":63,"height":63}},"lz18":{"lz3":{"type":"mesh","uvs":[1,1,0,1,0,0,1,0],"triangles":[1,2,3,1,3,0],"vertices":[26.44,-26.37,-27.56,-26.37,-27.56,27.63,26.44,27.63],"hull":4,"edges":[0,2,2,4,4,6,0,6],"width":54,"height":54}},"lz19":{"lz2":{"type":"mesh","uvs":[1,1,0,1,0,0,1,0],"triangles":[1,2,3,1,3,0],"vertices":[20.52,-20.36,-20.48,-20.36,-20.48,20.64,20.52,20.64],"hull":4,"edges":[0,2,2,4,4,6,0,6],"width":41,"height":41}},"lz20":{"lz1":{"type":"mesh","uvs":[1,1,0,1,0,0,1,0],"triangles":[1,2,3,1,3,0],"vertices":[20.22,-20.14,-20.78,-20.14,-20.78,20.86,20.22,20.86],"hull":4,"edges":[0,2,2,4,4,6,0,6],"width":41,"height":41}},"x1":{"x1":{"type":"mesh","uvs":[1,1,0,1,0,0,1,0],"triangles":[1,2,3,1,3,0],"vertices":[48.68,-48.32,-43.32,-48.32,-43.32,43.68,48.68,43.68],"hull":4,"edges":[0,2,2,4,4,6,0,6],"width":92,"height":92}},"x2":{"x2":{"type":"mesh","uvs":[1,1,0,1,0,0,1,0],"triangles":[1,2,3,1,3,0],"vertices":[44.01,-45.65,-46.99,-45.65,-46.99,45.35,44.01,45.35],"hull":4,"edges":[0,2,2,4,4,6,0,6],"width":91,"height":91}},"x3":{"x3":{"type":"mesh","uvs":[1,1,0,1,0,0,1,0],"triangles":[1,2,3,1,3,0],"vertices":[48.48,-46.95,-45.52,-46.95,-45.52,43.05,48.48,43.05],"hull":4,"edges":[0,2,2,4,4,6,0,6],"width":94,"height":90}},"x4":{"x4":{"type":"mesh","uvs":[1,1,0,1,0,0,1,0],"triangles":[1,2,3,1,3,0],"vertices":[47.42,-41.37,-48.58,-41.37,-48.58,48.63,47.42,48.63],"hull":4,"edges":[0,2,2,4,4,6,0,6],"width":96,"height":90}},"x5":{"x5":{"type":"mesh","uvs":[1,1,0,1,0,0,1,0],"triangles":[1,2,3,1,3,0],"vertices":[48.04,-50.12,-45.96,-50.12,-45.96,43.88,48.04,43.88],"hull":4,"edges":[0,2,2,4,4,6,0,6],"width":94,"height":94}},"x6":{"x6":{"type":"mesh","uvs":[1,1,0,1,0,0,1,0],"triangles":[1,2,3,1,3,0],"vertices":[42.98,-48.34,-48.02,-48.34,-48.02,45.66,42.98,45.66],"hull":4,"edges":[0,2,2,4,4,6,0,6],"width":91,"height":94}},"x7":{"x1":{"type":"mesh","uvs":[1,1,0,1,0,0,1,0],"triangles":[1,2,3,1,3,0],"vertices":[48.68,-48.32,-43.32,-48.32,-43.32,43.68,48.68,43.68],"hull":4,"edges":[0,2,2,4,4,6,0,6],"width":92,"height":92}},"x8":{"x4":{"type":"mesh","uvs":[1,1,0,1,0,0,1,0],"triangles":[1,2,3,1,3,0],"vertices":[47.42,-41.37,-48.58,-41.37,-48.58,48.63,47.42,48.63],"hull":4,"edges":[0,2,2,4,4,6,0,6],"width":96,"height":90}},"yuan1":{"yuan1":{"type":"mesh","uvs":[1,1,0,1,0,0,1,0],"triangles":[1,2,3,1,3,0],"vertices":[-262.5,-261.5,-262.5,262.5,262.5,262.5,262.5,-261.5],"hull":4,"edges":[0,2,2,4,4,6,0,6],"width":524,"height":525}},"yuan2":{"yuan2":{"type":"mesh","uvs":[1,1,0,1,0,0,1,0],"triangles":[1,2,3,1,3,0],"vertices":[219.5,-219.5,-219.5,-219.5,-219.5,219.5,219.5,219.5],"hull":4,"edges":[0,2,2,4,4,6,0,6],"width":439,"height":439}}}}],"animations":{"animation":{"slots":{"d1":{"color":[{"time":0.4,"color":"ffffffff","curve":0.25,"c3":0.75},{"time":0.6333,"color":"ffffff00"}]},"d2":{"color":[{"time":1.0333,"color":"ffffffff","curve":0.25,"c3":0.75},{"time":1.2333,"color":"ffffff00"}]},"d3":{"color":[{"time":0.9333,"color":"ffffffff","curve":0.25,"c3":0.75},{"time":1.1333,"color":"ffffff00"}]},"d4":{"color":[{"time":0.4667,"color":"ffffffff","curve":0.25,"c3":0.75},{"time":0.7,"color":"ffffff00"}]},"d5":{"color":[{"time":1.0333,"color":"ffffffff","curve":0.25,"c3":0.75},{"time":1.2333,"color":"ffffff00"}]},"d6":{"color":[{"time":0.9333,"color":"ffffffff","curve":0.25,"c3":0.75},{"time":1.1333,"color":"ffffff00"}]},"d7":{"color":[{"time":0.9667,"color":"ffffffff","curve":0.25,"c3":0.75},{"time":1.1667,"color":"ffffff00"}]},"d8":{"color":[{"time":1.2,"color":"ffffffff","curve":0.25,"c3":0.75},{"time":1.4,"color":"ffffff00"}]},"f1":{"color":[{"time":1,"color":"ffffffff","curve":0.25,"c3":0.75},{"time":1.2333,"color":"ffffff00"}]},"f2":{"color":[{"time":0.8667,"color":"ffffffff","curve":0.25,"c3":0.75},{"time":1.1,"color":"ffffff00"}]},"f4":{"color":[{"time":0.8667,"color":"ffffffff","curve":0.25,"c3":0.75},{"time":1.1,"color":"ffffff00"}]},"f6":{"color":[{"time":0.8667,"color":"ffffffff","curve":0.25,"c3":0.75},{"time":1.1,"color":"ffffff00"}]},"l2":{"color":[{"time":0.8667,"color":"ffffffff","curve":0.25,"c3":0.75},{"time":1.1,"color":"ffffff00"}]},"l3":{"color":[{"time":0.9667,"color":"ffffffff","curve":0.25,"c3":0.75},{"time":1.1667,"color":"ffffff00"}]},"l5":{"color":[{"time":0.9333,"color":"ffffffff","curve":0.25,"c3":0.75},{"time":1.1333,"color":"ffffff00"}]},"l6":{"color":[{"time":0.9333,"color":"ffffffff","curve":0.25,"c3":0.75},{"time":1.1333,"color":"ffffff00"}]},"l7":{"color":[{"time":0.8,"color":"ffffffff","curve":0.25,"c3":0.75},{"time":1,"color":"ffffff00"}]},"l8":{"color":[{"time":0.9667,"color":"ffffffff","curve":0.25,"c3":0.75},{"time":1.1667,"color":"ffffff00"}]},"l9":{"color":[{"time":0.9333,"color":"ffffffff","curve":0.25,"c3":0.75},{"time":1.1333,"color":"ffffff00"}]},"l10":{"color":[{"time":1,"color":"ffffffff","curve":0.25,"c3":0.75},{"time":1.2,"color":"ffffff00"}]},"x1":{"color":[{"time":1.1333,"color":"ffffffff","curve":0.25,"c3":0.75},{"time":1.3333,"color":"ffffff00"}]},"x2":{"color":[{"time":0.9333,"color":"ffffffff","curve":0.25,"c3":0.75},{"time":1.1333,"color":"ffffff00"}]},"x5":{"color":[{"time":0.9333,"color":"ffffffff","curve":0.25,"c3":0.75},{"time":1.1333,"color":"ffffff00"}]},"x8":{"color":[{"time":0.8667,"color":"ffffffff","curve":0.25,"c3":0.75},{"time":1.0667,"color":"ffffff00"}]}},"bones":{"dk_body":{"rotate":[{"angle":16.03,"curve":0.25,"c3":0},{"time":0.2333,"curve":0.25,"c3":0.75},{"time":0.6333,"angle":-0.69,"curve":0.25,"c3":0.75},{"time":1.0333,"angle":4.46}]},"dk_body2":{"rotate":[{"angle":14.62,"curve":"stepped"},{"time":0.0333,"angle":14.62,"curve":0.25,"c3":0},{"time":0.2667,"curve":0.25,"c3":0.75},{"time":0.7,"angle":-0.69,"curve":0.25,"c3":0.75},{"time":1.0333,"angle":4.46}],"translate":[{"x":-12.84,"y":-0.96,"curve":"stepped"},{"time":0.0333,"x":-12.84,"y":-0.96,"curve":0.25,"c3":0},{"time":0.2667,"curve":0.25,"c3":0.75},{"time":0.7,"x":4.96,"y":-0.1,"curve":0.25,"c3":0.75},{"time":1.0333,"x":-2.5,"y":-0.21}]},"dk_tou":{"rotate":[{"angle":6.96,"curve":"stepped"},{"time":0.0667,"angle":6.96,"curve":0.25,"c3":0},{"time":0.3,"curve":0.25,"c3":0.75},{"time":0.7,"angle":-0.69,"curve":0.25,"c3":0.75},{"time":1.0667,"angle":4.46}]},"dk_zsb":{"rotate":[{"angle":44.94,"curve":"stepped"},{"time":0.0667,"angle":44.94,"curve":0.25,"c3":0},{"time":0.3,"angle":-32.44,"curve":0.107,"c2":0.09,"c3":0.75},{"time":0.7,"angle":-42.04,"curve":0.25,"c3":0.75},{"time":1.1,"angle":25.23}]},"dk_zxb":{"rotate":[{"angle":2.35,"curve":"stepped"},{"time":0.1333,"angle":2.35,"curve":0.25,"c3":0},{"time":0.3,"angle":-12.96,"curve":0.107,"c2":0.09,"c3":0.75},{"time":0.7,"angle":-22.55,"curve":0.25,"c3":0.75},{"time":1.1667,"angle":-4.84}]},"dk_ysb":{"rotate":[{"angle":-58.24,"curve":"stepped"},{"time":0.0667,"angle":-58.24,"curve":0.25,"c3":0},{"time":0.3,"angle":48.68,"curve":0.107,"c2":0.09,"c3":0.75},{"time":0.7,"angle":61.39,"curve":0.25,"c3":0.75},{"time":1.1,"angle":-23.87}]},"dk_yxb":{"rotate":[{"angle":-1.22,"curve":"stepped"},{"time":0.1333,"angle":-1.22,"curve":0.25,"c3":0},{"time":0.3,"angle":20.24,"curve":0.107,"c2":0.09,"c3":0.75},{"time":0.7,"angle":32.94,"curve":0.25,"c3":0.75},{"time":1.1667,"angle":8.48}]},"dk_zst":{"rotate":[{"angle":47.13,"curve":0.25,"c3":0},{"time":0.2667,"angle":-18.26,"curve":0.107,"c2":0.09,"c3":0.75},{"time":0.7,"angle":-33.4,"curve":0.25,"c3":0.75},{"time":1.0333,"angle":25.6}]},"dk_zxt":{"rotate":[{"angle":3.56,"curve":"stepped"},{"time":0.0667,"angle":3.56,"curve":0.25,"c3":0},{"time":0.3333,"curve":0.107,"c2":0.09,"c3":0.75},{"time":0.7667,"angle":-15.14,"curve":0.25,"c3":0.75},{"time":1.1667,"angle":39.22}]},"dk_yst":{"rotate":[{"angle":-28.11,"curve":0.25,"c3":0},{"time":0.2667,"angle":38.29,"curve":0.107,"c2":0.09,"c3":0.75},{"time":0.7,"angle":55.19,"curve":0.25,"c3":0.75},{"time":1.0333,"angle":-13.13}]},"dk_yxt":{"rotate":[{"angle":-0.64,"curve":"stepped"},{"time":0.0667,"angle":-0.64,"curve":0.25,"c3":0},{"time":0.3333,"curve":0.107,"c2":0.09,"c3":0.75},{"time":0.7667,"angle":16.9,"curve":0.25,"c3":0.75},{"time":1.1667,"angle":-29.68}]},"dk_bz":{"translate":[{"x":-39.38,"y":2.06,"curve":"stepped"},{"time":0.1,"x":-39.38,"y":2.06,"curve":0.25,"c3":0},{"time":0.3333,"curve":0.25,"c3":0.75},{"time":0.7333,"x":12.76,"curve":0.25,"c3":0.75},{"time":1.1,"x":-20.7,"y":0.44}]},"bone":{"translate":[{"y":-842.55,"curve":0.25,"c3":0.057},{"time":0.2333,"curve":0.045,"c2":0.08,"c3":0.222},{"time":0.6333,"y":29.33,"curve":0.686,"c3":0.915,"c4":0.5},{"time":1,"x":145.05,"y":-959.55}],"scale":[{"y":0.922,"curve":0.25,"c3":0},{"time":0.2333,"curve":0.25,"c3":0.75},{"time":0.6333,"y":1.018,"curve":0.986,"c3":0.75},{"time":1}]},"dk_x":{"rotate":[{"angle":58.21,"curve":0.25,"c3":0},{"time":0.3333,"angle":-5.64,"curve":0.25,"c3":0.75},{"time":0.7333,"angle":-16.05,"curve":0.25,"c3":0.75},{"time":1.1,"angle":35.6}]},"dk_x2":{"rotate":[{"angle":58.21,"curve":0.25,"c3":0},{"time":0.3667,"angle":-5.64,"curve":0.25,"c3":0.75},{"time":0.8,"angle":-16.05,"curve":0.25,"c3":0.75},{"time":1.1333,"angle":31.69}]},"dk_q":{"rotate":[{"angle":58.21,"curve":0.25,"c3":0},{"time":0.4,"angle":-5.64,"curve":0.25,"c3":0.75},{"time":0.8333,"angle":-16.05,"curve":0.25,"c3":0.75},{"time":1.1667,"angle":31.69}]},"dk_zui":{"scale":[{"x":0.425,"y":0.769,"curve":"stepped"},{"time":0.1,"x":0.425,"y":0.769,"curve":0.25,"c3":0},{"time":0.3333,"curve":0.25,"c3":0.75},{"time":0.7333,"x":1.234,"y":1.07,"curve":0.25,"c3":0.75},{"time":1.1,"x":0.535,"y":0.835}]},"d1":{"translate":[{"x":-121.68,"y":-693.04,"curve":0.087,"c2":0.61,"c3":0,"c4":0.97},{"time":0.6333,"x":347.33,"y":897.83}]},"x6":{"rotate":[{"curve":0.25,"c3":0.75},{"time":0.1,"angle":29.4,"curve":0.25,"c3":0.75},{"time":0.8333,"angle":-48.23,"curve":0.25,"c3":0.75},{"time":1.4667,"angle":-128.64}],"translate":[{"x":-5.1,"y":-641.96,"curve":"stepped"},{"time":0.1,"x":-5.1,"y":-641.96,"curve":0.087,"c2":0.61,"c3":0.052,"c4":0.95},{"time":0.8333,"x":-25.2,"y":254.3,"curve":0.25,"c3":0.75},{"time":1.4667,"x":-25.2,"y":-322.91}],"scale":[{"time":0.8333,"curve":0.25,"c3":0.75},{"time":1.4667,"x":0,"y":0}]},"l3":{"rotate":[{"time":0.0333,"curve":0.25,"c3":0.75},{"time":1.4333,"angle":-65.88}],"translate":[{"x":-120.51,"y":-866.23,"curve":"stepped"},{"time":0.0333,"x":-120.51,"y":-866.23,"curve":0.087,"c2":0.61,"c3":0.052,"c4":0.95},{"time":0.8,"x":25.2,"y":135.17,"curve":0.25,"c3":0.75},{"time":1.4333,"x":25.2,"y":-442.04}],"scale":[{"time":0.8,"curve":0.25,"c3":0.75},{"time":1.4333,"x":0,"y":0}]},"l2":{"rotate":[{"curve":0.25,"c3":0.75},{"time":0.7,"angle":73.46,"curve":0.25,"c3":0.75},{"time":1.3333,"angle":133.28}],"translate":[{"x":-106.59,"y":-977.74,"curve":0.087,"c2":0.61,"c3":0.052,"c4":0.95},{"time":0.7,"curve":0.25,"c3":0.75},{"time":1.3333,"y":-577.21}],"scale":[{"time":0.7,"curve":0.25,"c3":0.75},{"time":1.3333,"x":0,"y":0}]},"d6":{"rotate":[{"curve":0.25,"c3":0.75},{"time":0.7333,"angle":-63.07,"curve":0.25,"c3":0.75},{"time":1.4,"angle":-161.04}],"translate":[{"x":8.49,"y":-801.66,"curve":0.087,"c2":0.61,"c3":0.052,"c4":0.95},{"time":0.7333,"curve":0.25,"c3":0.75},{"time":1.4,"y":-577.21}],"scale":[{"time":0.7333,"curve":0.25,"c3":0.75},{"time":1.4,"x":0,"y":0}]},"l7":{"rotate":[{"curve":0.25,"c3":0.75},{"time":0.6333,"angle":61.81,"curve":0.25,"c3":0.75},{"time":1.3,"angle":108.96}],"translate":[{"x":-108.74,"y":-1144.86,"curve":0.087,"c2":0.61,"c3":0.052,"c4":0.95},{"time":0.6333,"curve":0.25,"c3":0.75},{"time":1.3,"y":-577.21}],"scale":[{"time":0.6333,"curve":0.25,"c3":0.75},{"time":1.3,"x":0,"y":0}]},"x4":{"rotate":[{"time":0.0667,"curve":0.25,"c3":0.75},{"time":0.8,"angle":86.46,"curve":0.25,"c3":0.75},{"time":1.3,"angle":-174.11}],"translate":[{"x":-129.75,"y":-890.57,"curve":"stepped"},{"time":0.0667,"x":-129.75,"y":-890.57,"curve":0.087,"c2":0.61,"c3":0.052,"c4":0.95},{"time":0.8,"x":4.58,"y":-4.58,"curve":0.25,"c3":0.75},{"time":1.3,"x":4.58,"y":-581.79}],"scale":[{"time":0.8,"curve":0.25,"c3":0.75},{"time":1.3,"x":0,"y":0}]},"x7":{"rotate":[{"curve":0.25,"c3":0.75},{"time":0.7333,"angle":-59.13,"curve":0.25,"c3":0.75},{"time":1.4,"angle":-95.73}],"translate":[{"x":-5.25,"y":-1253.09,"curve":0.087,"c2":0.61,"c3":0.052,"c4":0.95},{"time":0.7333,"curve":0.25,"c3":0.75},{"time":1.4,"y":-577.21}],"scale":[{"time":0.7333,"curve":0.25,"c3":0.75},{"time":1.4,"x":0,"y":0}]},"f6":{"rotate":[{"time":0.0333,"curve":0.25,"c3":0.75},{"time":1.3333,"angle":-96.16}],"translate":[{"x":-53.47,"y":-1054.59,"curve":"stepped"},{"time":0.0333,"x":-53.47,"y":-1054.59,"curve":0.087,"c2":0.61,"c3":0.052,"c4":0.95},{"time":0.7333,"curve":0.25,"c3":0.75},{"time":1.3333,"y":-577.21}],"scale":[{"time":0.7333,"curve":0.25,"c3":0.75},{"time":1.3333,"x":0,"y":0}]},"d7":{"rotate":[{"time":0.0333,"angle":-62.78,"curve":0.25,"c3":0.75},{"time":0.8,"angle":-12.41,"curve":0.25,"c3":0.75},{"time":1.4333,"angle":56.24}],"translate":[{"x":26.26,"y":-1203.19,"curve":"stepped"},{"time":0.0333,"x":26.26,"y":-1203.19,"curve":0.087,"c2":0.61,"c3":0.052,"c4":0.95},{"time":0.8,"curve":0.25,"c3":0.75},{"time":1.4333,"y":-577.21}],"scale":[{"time":0.8,"curve":0.25,"c3":0.75},{"time":1.4333,"x":0,"y":0}]},"l1":{"rotate":[{"time":0.0333,"curve":0.25,"c3":0.75},{"time":1.4333,"angle":-110.34}],"translate":[{"x":53.44,"y":-1236.62,"curve":"stepped"},{"time":0.0333,"x":53.44,"y":-1236.62,"curve":0.087,"c2":0.61,"c3":0.052,"c4":0.95},{"time":0.8,"curve":0.25,"c3":0.75},{"time":1.4333,"y":-577.21}],"scale":[{"time":0.8,"curve":0.25,"c3":0.75},{"time":1.4333,"x":0,"y":0}]},"x2":{"rotate":[{"curve":0.25,"c3":0.75},{"time":0.7333,"angle":-86.11,"curve":0.25,"c3":0.75},{"time":1.4,"angle":178.79}],"translate":[{"x":-191.59,"y":-1329.24,"curve":0.087,"c2":0.61,"c3":0.052,"c4":0.95},{"time":0.7333,"curve":0.25,"c3":0.75},{"time":1.4,"y":-577.21}],"scale":[{"time":0.7333,"curve":0.25,"c3":0.75},{"time":1.4,"x":0,"y":0}]},"l4":{"rotate":[{"time":0.1,"curve":0.25,"c3":0.75},{"time":0.8667,"angle":-80.45,"curve":0.25,"c3":0.75},{"time":1.5,"angle":156.13}],"translate":[{"x":-47.85,"y":-617.26,"curve":"stepped"},{"time":0.1,"x":-47.85,"y":-617.26,"curve":0.087,"c2":0.61,"c3":0.052,"c4":0.95},{"time":0.8667,"x":-13.75,"y":142.04,"curve":0.25,"c3":0.75},{"time":1.5,"x":-13.75,"y":-435.17}],"scale":[{"time":0.8667,"curve":0.25,"c3":0.75},{"time":1.5,"x":0,"y":0}]},"f5":{"rotate":[{"curve":0.25,"c3":0.75},{"time":1.4,"angle":125.74}],"translate":[{"x":45.5,"y":-475.16,"curve":0.087,"c2":0.61,"c3":0.052,"c4":0.95},{"time":0.7333,"x":52.69,"y":426.13,"curve":0.25,"c3":0.75},{"time":1.4,"x":52.69,"y":-151.08}],"scale":[{"time":0.7333,"curve":0.25,"c3":0.75},{"time":1.4,"x":0,"y":0}]},"f1":{"translate":[{"x":-22.75,"y":-679.89,"curve":"stepped"},{"time":0.1,"x":-22.75,"y":-679.89,"curve":0.087,"c2":0.61,"c3":0.052,"c4":0.95},{"time":0.8333,"curve":0.25,"c3":0.75},{"time":1.4667,"y":-577.21}],"scale":[{"time":0.8333,"curve":0.25,"c3":0.75},{"time":1.4667,"x":0,"y":0}]},"d4":{"translate":[{"x":93.54,"y":-923.88,"curve":0.087,"c2":0.61,"c3":0.052,"c4":0.95},{"time":0.7}]},"d5":{"rotate":[{"time":0.1,"curve":0.25,"c3":0.75},{"time":1.5,"angle":98.95}],"translate":[{"x":170.45,"y":-818.64,"curve":"stepped"},{"time":0.1,"x":170.45,"y":-818.64,"curve":0.087,"c2":0.61,"c3":0.052,"c4":0.95},{"time":0.8667,"curve":0.25,"c3":0.75},{"time":1.5,"y":-577.21}],"scale":[{"time":0.8667,"curve":0.25,"c3":0.75},{"time":1.5,"x":0,"y":0}]},"l6":{"rotate":[{"curve":0.25,"c3":0.75},{"time":1.4,"angle":166.57}],"translate":[{"x":260.67,"y":-840.72,"curve":0.087,"c2":0.61,"c3":0.052,"c4":0.95},{"time":0.7333,"curve":0.25,"c3":0.75},{"time":1.4,"y":-577.21}],"scale":[{"time":0.7333,"curve":0.25,"c3":0.75},{"time":1.4,"x":0,"y":0}]},"x1":{"rotate":[{"time":0.0333,"curve":0.25,"c3":0.75},{"time":1.3333,"angle":-165.72}],"translate":[{"x":43.72,"y":-844.13,"curve":"stepped"},{"time":0.0333,"x":43.72,"y":-844.13,"curve":0.087,"c2":0.61,"c3":0.052,"c4":0.95},{"time":0.8,"x":-45.82,"y":247.43,"curve":0.25,"c3":0.75},{"time":1.3333,"x":-45.82,"y":-329.78}],"scale":[{"time":0.8,"curve":0.25,"c3":0.75},{"time":1.3333,"x":0,"y":0}]},"f2":{"rotate":[{"curve":0.25,"c3":0.75},{"time":1.3333,"angle":-111.05}],"translate":[{"x":-23.64,"y":-1245.21,"curve":0.087,"c2":0.61,"c3":0.052,"c4":0.95},{"time":0.7,"curve":0.25,"c3":0.75},{"time":1.3333,"y":-577.21}],"scale":[{"time":0.7,"curve":0.25,"c3":0.75},{"time":1.3333,"x":0,"y":0}]},"f3":{"rotate":[{"angle":-27.64,"curve":0.25,"c3":0.75},{"time":0.7333,"curve":0.25,"c3":0.75},{"time":1.2667,"angle":45.24}],"translate":[{"x":-47.27,"y":-1289.85,"curve":0.087,"c2":0.61,"c3":0.052,"c4":0.95},{"time":0.7333,"curve":0.25,"c3":0.75},{"time":1.2667,"y":-577.21}],"scale":[{"time":0.7333,"curve":0.25,"c3":0.75},{"time":1.2667,"x":0,"y":0}]},"x3":{"rotate":[{"curve":0.25,"c3":0.75},{"time":1.4,"angle":-154.43}],"translate":[{"x":-47.27,"y":-1239.96,"curve":0.087,"c2":0.61,"c3":0.052,"c4":0.95},{"time":0.7333,"curve":0.25,"c3":0.75},{"time":1.4,"y":-577.21}],"scale":[{"time":0.7333,"curve":0.25,"c3":0.75},{"time":1.4,"x":0,"y":0}]},"d2":{"rotate":[{"time":0.1,"curve":0.25,"c3":0.75},{"time":1.5,"angle":-94.13}],"translate":[{"x":-18.74,"y":-581.8,"curve":"stepped"},{"time":0.1,"x":-18.74,"y":-581.8,"curve":0.087,"c2":0.61,"c3":0.052,"c4":0.95},{"time":0.8667,"x":-43.53,"y":192.44,"curve":0.25,"c3":0.75},{"time":1.5,"x":-43.53,"y":-384.76}],"scale":[{"time":0.8667,"curve":0.25,"c3":0.75},{"time":1.5,"x":0,"y":0}]},"x5":{"rotate":[{"curve":0.25,"c3":0.75},{"time":1.4,"angle":143.42}],"translate":[{"x":26.03,"y":-940.38,"curve":0.087,"c2":0.61,"c3":0.052,"c4":0.95},{"time":0.7333,"curve":0.25,"c3":0.75},{"time":1.4,"y":-577.21}],"scale":[{"time":0.7333,"curve":0.25,"c3":0.75},{"time":1.4,"x":0,"y":0}]},"f4":{"rotate":[{"time":0.0333,"curve":0.25,"c3":0.75},{"time":1.3333,"angle":-104.3}],"translate":[{"x":10.96,"y":-662.12,"curve":"stepped"},{"time":0.0333,"x":10.96,"y":-662.12,"curve":0.087,"c2":0.61,"c3":0.052,"c4":0.95},{"time":0.7333,"x":-61.86,"y":199.32,"curve":0.25,"c3":0.75},{"time":1.3333,"x":-61.86,"y":-377.89}],"scale":[{"time":0.7333,"curve":0.25,"c3":0.75},{"time":1.3333,"x":0,"y":0}]},"d3":{"translate":[{"x":35.16,"y":-1184.48,"curve":0.087,"c2":0.61,"c3":0.052,"c4":0.95},{"time":0.7333,"curve":0.25,"c3":0.75},{"time":1.4,"y":-577.21}],"scale":[{"time":0.7333,"curve":0.25,"c3":0.75},{"time":1.4,"x":0,"y":0}]},"l5":{"rotate":[{"curve":0.25,"c3":0.75},{"time":0.7333,"angle":135.59,"curve":0.25,"c3":0.75},{"time":1.3667,"angle":-102.2}],"translate":[{"x":-39.29,"y":-1250.66,"curve":0.087,"c2":0.61,"c3":0.052,"c4":0.95},{"time":0.7333,"curve":0.25,"c3":0.75},{"time":1.4,"y":-577.21}],"scale":[{"time":0.7333,"curve":0.25,"c3":0.75},{"time":1.4,"x":0,"y":0}]},"l8":{"rotate":[{"time":0.0333,"curve":0.25,"c3":0.75},{"time":1.4333,"angle":124.53}],"translate":[{"x":77.03,"y":-1046.09,"curve":"stepped"},{"time":0.0333,"x":77.03,"y":-1046.09,"curve":0.087,"c2":0.61,"c3":0.052,"c4":0.95},{"time":0.8,"x":-194.73,"y":536.09,"curve":0.25,"c3":0.75},{"time":1.4333,"x":-194.73,"y":-41.11}],"scale":[{"time":0.8,"curve":0.25,"c3":0.75},{"time":1.4333,"x":0,"y":0}]},"x8":{"rotate":[{"curve":0.25,"c3":0.75},{"time":1.2333,"angle":162.14}],"translate":[{"x":102.13,"y":-701.41,"curve":0.087,"c2":0.61,"c3":0.052,"c4":0.95},{"time":0.6667,"x":11.45,"y":226.81,"curve":0.25,"c3":0.75},{"time":1.2333,"x":11.45,"y":-350.4}],"scale":[{"time":0.6667,"curve":0.25,"c3":0.75},{"time":1.2333,"x":0,"y":0}]},"l9":{"rotate":[{"angle":-0.8,"curve":0.25,"c3":0.75},{"time":1.4,"angle":85.02}],"translate":[{"y":-1329.24,"curve":0.087,"c2":0.61,"c3":0.052,"c4":0.95},{"time":0.7333,"curve":0.25,"c3":0.75},{"time":1.4,"y":-577.21}],"scale":[{"time":0.7333,"curve":0.25,"c3":0.75},{"time":1.4,"x":0,"y":0}]},"l10":{"rotate":[{"time":0.0667,"curve":0.25,"c3":0.75},{"time":0.8,"angle":69.7,"curve":0.25,"c3":0.75},{"time":1.4667,"angle":131.7}],"translate":[{"x":53.49,"y":-1163.8,"curve":"stepped"},{"time":0.0667,"x":53.49,"y":-1163.8,"curve":0.087,"c2":0.61,"c3":0.052,"c4":0.95},{"time":0.8,"curve":0.25,"c3":0.75},{"time":1.4667,"y":-577.21}],"scale":[{"time":0.8,"curve":0.25,"c3":0.75},{"time":1.4667,"x":0,"y":0}]},"d8":{"translate":[{"y":-1329.24,"curve":"stepped"},{"time":0.0333,"y":-1329.24,"curve":0.087,"c2":0.61,"c3":0.052,"c4":0.95},{"time":0.7667,"curve":0.25,"c3":0.75},{"time":1.4,"y":-577.21}],"scale":[{"time":0.7667,"curve":0.25,"c3":0.75},{"time":1.4,"x":0,"y":0}]},"lz1":{"translate":[{"x":-49.93,"y":81.95,"curve":"stepped"},{"time":0.2667,"x":-49.93,"y":81.95,"curve":0.25,"c3":0.469},{"time":0.5667}],"scale":[{"x":0,"y":0,"curve":"stepped"},{"time":0.2667,"x":0,"y":0,"curve":0.25,"c3":0.469},{"time":0.3333,"curve":"stepped"},{"time":0.4667,"curve":0.25,"c3":0.75},{"time":0.5667,"x":0,"y":0}]},"lz2":{"translate":[{"x":47.1,"y":-2.83,"curve":"stepped"},{"time":0.2333,"x":47.1,"y":-2.83,"curve":0.25,"c3":0.469},{"time":0.5}],"scale":[{"x":0,"y":0,"curve":"stepped"},{"time":0.2333,"x":0,"y":0,"curve":0.25,"c3":0.469},{"time":0.3,"curve":"stepped"},{"time":0.4,"curve":0.25,"c3":0.75},{"time":0.5,"x":0,"y":0}]},"lz3":{"translate":[{"x":-152.68,"y":338.17,"curve":"stepped"},{"time":0.2,"x":-152.68,"y":338.17,"curve":0.25,"c3":0.75},{"time":0.4667}],"scale":[{"x":0,"y":0,"curve":"stepped"},{"time":0.2,"x":0,"y":0,"curve":0.25,"c3":0.75},{"time":0.2667,"curve":"stepped"},{"time":0.3667,"curve":0.25,"c3":0.75},{"time":0.4667,"x":0,"y":0}]},"lz4":{"translate":[{"x":292.02,"y":-1.88,"curve":"stepped"},{"time":0.2,"x":292.02,"y":-1.88,"curve":0.25,"c3":0.469},{"time":0.5}],"scale":[{"x":0,"y":0,"curve":"stepped"},{"time":0.2,"x":0,"y":0,"curve":0.25,"c3":0.469},{"time":0.2667,"curve":"stepped"},{"time":0.4,"curve":0.25,"c3":0.75},{"time":0.5,"x":0,"y":0}]},"lz5":{"translate":[{"x":-103.62,"y":29.2,"curve":"stepped"},{"time":0.2667,"x":-103.62,"y":29.2,"curve":0.25,"c3":0.469},{"time":0.5333}],"scale":[{"x":0,"y":0,"curve":"stepped"},{"time":0.2667,"x":0,"y":0,"curve":0.25,"c3":0.469},{"time":0.3333,"curve":"stepped"},{"time":0.4333,"curve":0.25,"c3":0.75},{"time":0.5333,"x":0,"y":0}]},"lz6":{"translate":[{"x":237.38,"y":15.07,"curve":"stepped"},{"time":0.2,"x":237.38,"y":15.07,"curve":0.25,"c3":0.469},{"time":0.4667}],"scale":[{"x":0,"y":0,"curve":"stepped"},{"time":0.2,"x":0,"y":0,"curve":0.25,"c3":0.469},{"time":0.2667,"curve":"stepped"},{"time":0.3667,"curve":0.25,"c3":0.75},{"time":0.4667,"x":0,"y":0}]},"lz7":{"translate":[{"x":114.92,"y":-171.44,"curve":"stepped"},{"time":0.2333,"x":114.92,"y":-171.44,"curve":0.25,"c3":0.469},{"time":0.5}],"scale":[{"x":0,"y":0,"curve":"stepped"},{"time":0.2333,"x":0,"y":0,"curve":0.25,"c3":0.469},{"time":0.3,"curve":"stepped"},{"time":0.4,"curve":0.25,"c3":0.75},{"time":0.5,"x":0,"y":0}]},"lz8":{"translate":[{"x":-192.17,"y":182.75,"curve":"stepped"},{"time":0.2,"x":-192.17,"y":182.75,"curve":0.25,"c3":0.469},{"time":0.4667}],"scale":[{"x":0,"y":0,"curve":"stepped"},{"time":0.2,"x":0,"y":0,"curve":0.25,"c3":0.469},{"time":0.2667,"curve":"stepped"},{"time":0.3667,"curve":0.25,"c3":0.75},{"time":0.4667,"x":0,"y":0}]},"lz9":{"translate":[{"x":-198.76,"y":39.56,"curve":"stepped"},{"time":0.2,"x":-198.76,"y":39.56,"curve":0.25,"c3":0.469},{"time":0.4667}],"scale":[{"x":0,"y":0,"curve":"stepped"},{"time":0.2,"x":0,"y":0,"curve":0.25,"c3":0.469},{"time":0.2667,"curve":"stepped"},{"time":0.3667,"curve":0.25,"c3":0.75},{"time":0.4667,"x":0,"y":0}]},"lz10":{"translate":[{"x":-272.24,"y":-148.84,"curve":"stepped"},{"time":0.2,"x":-272.24,"y":-148.84,"curve":0.25,"c3":0.469},{"time":0.4667}],"scale":[{"x":0,"y":0,"curve":"stepped"},{"time":0.2,"x":0,"y":0,"curve":0.25,"c3":0.469},{"time":0.2667,"curve":"stepped"},{"time":0.3667,"curve":0.25,"c3":0.75},{"time":0.4667,"x":0,"y":0}]},"lz11":{"translate":[{"x":-272.24,"y":-148.84,"curve":"stepped"},{"time":0.3667,"x":-272.24,"y":-148.84,"curve":0.25,"c3":0.469},{"time":0.6333}],"scale":[{"x":0,"y":0,"curve":"stepped"},{"time":0.3667,"x":0,"y":0,"curve":0.25,"c3":0.469},{"time":0.4333,"curve":"stepped"},{"time":0.5667,"curve":0.25,"c3":0.75},{"time":0.6333,"x":0,"y":0}]},"lz12":{"translate":[{"x":-198.76,"y":39.56,"curve":"stepped"},{"time":0.3667,"x":-198.76,"y":39.56,"curve":0.25,"c3":0.469},{"time":0.6333}],"scale":[{"x":0,"y":0,"curve":"stepped"},{"time":0.3667,"x":0,"y":0,"curve":0.25,"c3":0.469},{"time":0.4333,"curve":"stepped"},{"time":0.5667,"curve":0.25,"c3":0.75},{"time":0.6333,"x":0,"y":0}]},"lz13":{"translate":[{"x":-192.17,"y":182.75,"curve":"stepped"},{"time":0.3667,"x":-192.17,"y":182.75,"curve":0.25,"c3":0.469},{"time":0.6333}],"scale":[{"x":0,"y":0,"curve":"stepped"},{"time":0.3667,"x":0,"y":0,"curve":0.25,"c3":0.469},{"time":0.4333,"curve":"stepped"},{"time":0.5667,"curve":0.25,"c3":0.75},{"time":0.6333,"x":0,"y":0}]},"lz14":{"translate":[{"x":114.92,"y":-171.44,"curve":"stepped"},{"time":0.4,"x":114.92,"y":-171.44,"curve":0.25,"c3":0.469},{"time":0.7}],"scale":[{"x":0,"y":0,"curve":"stepped"},{"time":0.4,"x":0,"y":0,"curve":0.25,"c3":0.469},{"time":0.5,"curve":"stepped"},{"time":0.6,"curve":0.25,"c3":0.75},{"time":0.7,"x":0,"y":0}]},"lz15":{"translate":[{"x":237.38,"y":15.07,"curve":"stepped"},{"time":0.3667,"x":237.38,"y":15.07,"curve":0.25,"c3":0.469},{"time":0.6333}],"scale":[{"x":0,"y":0,"curve":"stepped"},{"time":0.3667,"x":0,"y":0,"curve":0.25,"c3":0.469},{"time":0.4333,"curve":"stepped"},{"time":0.5667,"curve":0.25,"c3":0.75},{"time":0.6333,"x":0,"y":0}]},"lz16":{"translate":[{"x":-103.62,"y":29.2,"curve":"stepped"},{"time":0.4333,"x":-103.62,"y":29.2,"curve":0.25,"c3":0.469},{"time":0.7}],"scale":[{"x":0,"y":0,"curve":"stepped"},{"time":0.4333,"x":0,"y":0,"curve":0.25,"c3":0.469},{"time":0.5,"curve":"stepped"},{"time":0.6333,"curve":0.25,"c3":0.75},{"time":0.7,"x":0,"y":0}]},"lz17":{"translate":[{"x":292.02,"y":-1.88,"curve":"stepped"},{"time":0.4,"x":292.02,"y":-1.88,"curve":0.25,"c3":0.469},{"time":0.6667}],"scale":[{"x":0,"y":0,"curve":"stepped"},{"time":0.4,"x":0,"y":0,"curve":0.25,"c3":0.469},{"time":0.4667,"curve":"stepped"},{"time":0.5667,"curve":0.25,"c3":0.75},{"time":0.6667,"x":0,"y":0}]},"lz18":{"translate":[{"x":-152.68,"y":338.17,"curve":"stepped"},{"time":0.3667,"x":-152.68,"y":338.17,"curve":0.25,"c3":0.75},{"time":0.6333}],"scale":[{"x":0,"y":0,"curve":"stepped"},{"time":0.3667,"x":0,"y":0,"curve":0.25,"c3":0.469},{"time":0.4333,"curve":"stepped"},{"time":0.5667,"curve":0.25,"c3":0.75},{"time":0.6333,"x":0,"y":0}]},"lz19":{"translate":[{"x":47.1,"y":-2.83,"curve":"stepped"},{"time":0.4,"x":47.1,"y":-2.83,"curve":0.25,"c3":0.469},{"time":0.7}],"scale":[{"x":0,"y":0,"curve":"stepped"},{"time":0.4,"x":0,"y":0,"curve":0.25,"c3":0.469},{"time":0.5,"curve":"stepped"},{"time":0.6,"curve":0.25,"c3":0.75},{"time":0.7,"x":0,"y":0}]},"lz20":{"translate":[{"x":-49.93,"y":81.95,"curve":"stepped"},{"time":0.4667,"x":-49.93,"y":81.95,"curve":0.25,"c3":0.469},{"time":0.7333}],"scale":[{"x":0,"y":0,"curve":"stepped"},{"time":0.4667,"x":0,"y":0,"curve":0.25,"c3":0.469},{"time":0.5333,"curve":"stepped"},{"time":0.6333,"curve":0.25,"c3":0.75},{"time":0.7333,"x":0,"y":0}]}},"deform":{"default":{"dk_ycq":{"dk_ycq":[{"time":0.1333,"curve":0.25,"c3":0.75},{"time":0.3,"vertices":[12.04224,4.19684,-15.18701,-10.50793,0,0,12.10938,18.20551],"curve":0.107,"c2":0.09,"c3":0.75},{"time":0.7,"vertices":[23.09082,17.63831,-0.11829,-10.85999,0,0,17.29846,27.97858],"curve":0.25,"c3":0.75},{"time":1.1667}]},"dk_zcq":{"dk_zcq":[{"time":0.1333,"curve":0.25,"c3":0.75},{"time":0.3,"vertices":[-14.70468,11.0274,3.47098,2.81177,11.79572,-22.43134],"curve":0.107,"c2":0.09,"c3":0.75},{"time":0.7,"vertices":[-3.65695,14.28339,16.24478,-4.66919,16.03021,-34.93719],"curve":0.25,"c3":0.75},{"time":1.1667}]}}}}}}